Workbook

Sheet Stocks
A1: Date | B1: Ticker | C1: Asset Type | D1: Quantity | E1: Price | F1: Currency | G1: Investment | H1: Asset Name
A2: 45663 | B2: CSSPX.MI | C2: Stock | D2: 0.3257696 | F2: EUR | G2: 200 | H2: =_xlfn.XLOOKUP(B2,Mappings!$A$2:$A$10,Mappings!$B$2:$B$10) -> Google
A3: 45663 | B3: EUNL.DE | C3: Stock | D3: 1.889287 | F3: EUR | G3: 200 | H3: =_xlfn.XLOOKUP(B3,Mappings!$A$2:$A$10,Mappings!$B$2:$B$10) -> Nasdaq
A4: 45663 | B4: APC.DE | C4: ETF | D4: 0.844772 | F4: EUR | G4: 200 | H4: =_xlfn.XLOOKUP(B4,Mappings!$A$2:$A$10,Mappings!$B$2:$B$10) -> iShares Core S&P 500 UCITS ETF USD (Acc)
A5: 45686 | B5: XEON.DE | C5: ETF | D5: 3.927853 | F5: EUR | G5: 500 | H5: =_xlfn.XLOOKUP(B5,Mappings!$A$2:$A$10,Mappings!$B$2:$B$10) -> Xtrackers II EUR Overnight Rate Swap UCITS ETF 1C
A6: 45686 | B6: XEOD.DE | C6: ETF | D6: 3.927853 | F6: EUR | G6: 500 | H6: =_xlfn.XLOOKUP(B6,Mappings!$A$2:$A$10,Mappings!$B$2:$B$10) -> Xtrackers II EUR Overnight Rate Swap UCITS ETF 1D
A7: 45691 | B7: CSSPX.MI | C7: Stock | D7: 0.811661 | F7: EUR | G7: 500 | H7: =_xlfn.XLOOKUP(B7,Mappings!$A$2:$A$10,Mappings!$B$2:$B$10) -> Google
A8: 45691 | B8: VWCE.DE | C8: ETF | D8: 3.631873 | F8: EUR | G8: 500 | H8: =_xlfn.XLOOKUP(B8,Mappings!$A$2:$A$10,Mappings!$B$2:$B$10) -> iShares Global Water UCITS ETF USD (Dist)
A9: 45705 | B9: IQQQ.DE | C9: ETF | D9: 1.576789 | F9: EUR | G9: 100 | H9: =_xlfn.XLOOKUP(B9,Mappings!$A$2:$A$10,Mappings!$B$2:$B$10) -> iShares Core MSCI World UCITS ETF USD (Acc)
A10: 45719 | B10: CSSPX.MI | C10: Stock | D10: 0.82949 | F10: EUR | G10: 500 | H10: =_xlfn.XLOOKUP(B10,Mappings!$A$2:$A$10,Mappings!$B$2:$B$10) -> Google
A11: 45733 | B11: IQQQ.DE | C11: ETF | D11: 1.620745 | F11: EUR | G11: 100 | H11: =_xlfn.XLOOKUP(B11,Mappings!$A$2:$A$10,Mappings!$B$2:$B$10) -> iShares Core MSCI World UCITS ETF USD (Acc)
A12: 45749 | B12: CSSPX.MI | C12: Stock | D12: 0.907803 | F12: EUR | G12: 500 | H12: =_xlfn.XLOOKUP(B12,Mappings!$A$2:$A$10,Mappings!$B$2:$B$10) -> Google
A13: 45751 | B13: NAQ.F | C13: Stock | D13: 15.243902 | F13: EUR | G13: 1000.3 | H13: =_xlfn.XLOOKUP(B13,Mappings!$A$2:$A$10,Mappings!$B$2:$B$10) -> Vanguard FTSE All-World UCITS ETF USD Accumulation
A14: 45763 | B14: IQQQ.DE | C14: ETF | D14: 1.717327 | F14: EUR | G14: 100 | H14: =_xlfn.XLOOKUP(B14,Mappings!$A$2:$A$10,Mappings!$B$2:$B$10) -> iShares Core MSCI World UCITS ETF USD (Acc)
A15: 45763 | B15: IQQQ.DE | C15: ETF | D15: 1.576292 | E15: 63.65 | F15: EUR | G15: 100 | H15: =_xlfn.XLOOKUP(B15,Mappings!$A$2:$A$10,Mappings!$B$2:$B$10) -> iShares Core MSCI World UCITS ETF USD (Acc)
A16: 45779 | B16: 1GOOGL.MI | C16: Stock | D16: 0.346308 | F16: EUR | G16: 50 | H16: =_xlfn.XLOOKUP(B16,Mappings!$A$2:$A$10,Mappings!$B$2:$B$10) -> Apple Inc.
A17: 45779 | B17: NAQ.F | C17: ETF | D17: 0.73303 | F17: EUR | G17: 50 | H17: =_xlfn.XLOOKUP(B17,Mappings!$A$2:$A$10,Mappings!$B$2:$B$10) -> Vanguard FTSE All-World UCITS ETF USD Accumulation
A18: 45779 | B18: CSSPX.MI | C18: Stock | D18: 0.94568 | F18: EUR | G18: 500 | H18: =_xlfn.XLOOKUP(B18,Mappings!$A$2:$A$10,Mappings!$B$2:$B$10) -> Google
A19: 45779 | B19: VWCE.DE | C19: ETF | D19: 4.032908 | F19: EUR | G19: 500 | H19: =_xlfn.XLOOKUP(B19,Mappings!$A$2:$A$10,Mappings!$B$2:$B$10) -> iShares Global Water UCITS ETF USD (Dist)
A20: 45779 | B20: APC.DE | C20: ETF | D20: 0.272538 | E20: 183.46 | F20: EUR | G20: 50 | H20: =_xlfn.XLOOKUP(B20,Mappings!$A$2:$A$10,Mappings!$B$2:$B$10) -> iShares Core S&P 500 UCITS ETF USD (Acc)
A21: 45793 | B21: APC.DE | C21: ETF | D21: 0.264998 | E21: 188.68 | F21: EUR | G21: 50 | H21: =_xlfn.XLOOKUP(B21,Mappings!$A$2:$A$10,Mappings!$B$2:$B$10) -> iShares Core S&P 500 UCITS ETF USD (Acc)
A22: 45793 | B22: NAQ.F | C22: ETF | D22: 0.6854 | E22: 72.95 | F22: EUR | G22: 50 | H22: =_xlfn.XLOOKUP(B22,Mappings!$A$2:$A$10,Mappings!$B$2:$B$10) -> Vanguard FTSE All-World UCITS ETF USD Accumulation

Sheet Mappings
A1: Ticker | B1: Asset Name
A2: {=_xlfn.UNIQUE(Stocks!B2:B19)} -> CSSPX.MI | B2: Google
A3: EUNL.DE | B3: Nasdaq
A4: APC.DE | B4: iShares Core S&P 500 UCITS ETF USD (Acc)
A5: XEON.DE | B5: Xtrackers II EUR Overnight Rate Swap UCITS ETF 1C
A6: XEOD.DE | B6: Xtrackers II EUR Overnight Rate Swap UCITS ETF 1D
A7: VWCE.DE | B7: iShares Global Water UCITS ETF USD (Dist)
A8: IQQQ.DE | B8: iShares Core MSCI World UCITS ETF USD (Acc)
A9: NAQ.F | B9: Vanguard FTSE All-World UCITS ETF USD Accumulation
A10: 1GOOGL.MI | B10: Apple Inc.

Sheet BondsDividends
A1: WKN | B1: Date | C1: Amount
A2: A19387 | B2: 45809 | C2: 6.94
A3: A3LK3C | B3: 45869 | C3: 17.6
A4: A3LC3Y | B4: 45901 | C4: 55.47
A5: A19387 | B5: 45992 | C5: 6.94
A6: A2YN0A | B6: 46034 | C6: 5
A7: A3LK3C | B7: 46053 | C7: 17.6
A8: A3LC3Y | B8: 46082 | C8: 55.47
A9: A19387 | B9: 46174 | C9: 6.94
A10: A3LK3C | B10: 46234 | C10: 17.6
A11: A3LC3Y | B11: 46266 | C11: 55.47
A12: A19387 | B12: 46357 | C12: 6.94
A13: A2YN0A | B13: 46399 | C13: 5
... A61: A3LC3Y | B61: 52475 | C61: 55.47

Sheet IntDiv
A1: Date | B1: Quantity | C1: Asset
A2: 45778 | B2: 10.4 | C2: TR
A3: 45748 | B3: 12.05 | C3: TR
A4: 45717 | B4: 16.91 | C4: TR
A5: 45689 | B5: 19.83 | C5: TR
A6: 45689 | B6: 19.83 | C6: TR
A7: 45722 | B7: 7.42 | C7: Euro Swap
A8: 45701 | B8: 0.17 | C8: Apple Inc.

Sheet Bonds
A1: WKN | B1: ISIN | C1: Name | D1: Bond Type | E1: Maturity | F1: Currency | G1: Face Value | H1: Invested | I1: Coupon Redemption
A2: A3LC3Y | B2: IT0005530032 | C2: Italy | D2: Government | E2: 45565 | F2: EUR | H2: 2500
A3: A19387 | B3: IT0005340929 | C3: Italy | D3: Government | E3: 47118 | F3: EUR | H3: 500
A4: A2YN0A | B4: XS2282095970 | C4: Wolkswagen Leasing | D4: Corporate | E4: 47118 | F4: EUR | H4: 1000
A5: A3LK3C | B5: XS2648489388 | C5: Avis Budget Finance | D5: Corporate | E5: 47695 | F5: EUR | H5: 1000
